torment/__init__.py
torment/decorators.py
torment/helpers.py
torment/information.py
torment/contexts/__init__.py
torment/contexts/docker/__init__.py
torment/contexts/docker/compose.py
torment/fixtures/__init__.py
torment-3.0.3.data/data/share/doc/torment-3.0.3/README.rst
torment-3.0.3.dist-info/DESCRIPTION.rst
torment-3.0.3.dist-info/METADATA
torment-3.0.3.dist-info/RECORD
torment-3.0.3.dist-info/WHEEL
torment-3.0.3.dist-info/metadata.json
torment-3.0.3.dist-info/pbr.json
torment-3.0.3.dist-info/top_level.txt
