Metadata-Version: 2.0
Name: torment
Version: 3.0.3
Summary: A Study in Fixture Based Testing Frameworking
Home-page: https://github.com/kumoru/torment
Author: Alex Brandt
Author-email: alunduil@alunduil.com
License: Apache-2.0
Keywords: declarative,fixtures,framework,scalable,testing
Platform: UNKNOWN
Classifier: Development Status :: 4 - Beta
Classifier: Intended Audience :: Developers
Classifier: License :: OSI Approved :: Apache Software License
Classifier: Natural Language :: English
Classifier: Operating System :: OS Independent
Classifier: Programming Language :: Python :: 3
Classifier: Programming Language :: Python :: 3.4
Classifier: Programming Language :: Python :: 3.5
Classifier: Programming Language :: Python :: 3 :: Only
Classifier: Topic :: Software Development :: Libraries
Classifier: Topic :: Software Development :: Libraries :: Python Modules
Classifier: Topic :: Software Development :: Testing
Requires-Dist: mypy-lang
